fuzzyy/Adaline_Error_vs_Epoch _Graph.py
fuzzyy/Adaline_Implementation.py
fuzzyy/Compare_different_crossover_mutation_rates.py
fuzzyy/Hebbian_Learning_Binary_InputOutput.py
fuzzyy/Hebbian_Learning_Modified_Inputs.py
fuzzyy/Implement_GA_to_maximize.py
fuzzyy/McCulloch_Pitts_Neuron_for_OR_Gate.py
fuzzyy/McCulloch_Pitts_neuron_for_AND_gate.py
fuzzyy/SOM_Implementation _on_Data.py
fuzzyy/Visualizing_Neighbourhood_Effects.py
fuzzyy/XOR _Problem_with_Backpropagation.py
fuzzyy/__init__.py
fuzzyy/fuzzy_and_or _not_operation.py
fuzzyy/plot_triangular_and_trapezoidal _membership.py
fuzzyy/simple _fuzzy _inference _system_fis.py
fuzzyy-1.1.1.dist-info/licenses/LICENSE
fuzzyy-1.1.1.dist-info/METADATA
fuzzyy-1.1.1.dist-info/WHEEL
fuzzyy-1.1.1.dist-info/top_level.txt
fuzzyy-1.1.1.dist-info/RECORD
